{"type":"FeatureCollection","crs":{"type":"name","properties":{"name":"EPSG:4326"}},"features":[{"type":"Feature","id":3,"geometry":{"type":"Point","coordinates":[-85.0837379151447,38.3750597511628]},"properties":{"name":"HENRY COUNTY WATER DISTRICT #2","system":"HENRY COUNTY WATER DISTRICT #2","pwsid":"KY0520192","capacity":188,"use":"BOOSTER PUMP","type":"CENTRIFUGAL","pumps":2}},{"type":"Feature","id":7,"geometry":{"type":"Point","coordinates":[-85.1707794272482,38.4119894598613]},"properties":{"name":"HENRY COUNTY WATER DISTRICT #2","system":"HENRY COUNTY WATER DISTRICT #2","pwsid":"KY0520192","capacity":290,"use":"BOOSTER PUMP","type":"CENTRIFUGAL","pumps":2}},{"type":"Feature","id":8,"geometry":{"type":"Point","coordinates":[-85.1791176205271,38.4328173256711]},"properties":{"name":"HENRY COUNTY WATER DISTRICT #2","system":"HENRY COUNTY WATER DISTRICT #2","pwsid":"KY0520192","capacity":1400,"use":"BOOSTER PUMP","type":"CENTRIFUGAL","pumps":2}}]}